{
  "C.elegans": {
    "sigma": 7.63286568755189,
    "C": 0.2605108949194971,
    "L": 3.3800867589341044,
    "alpha": 1.9545304642109012,
    "el": 0.23852183650615902,
    "pass_sigma": 1,
    "pass_C": 1,
    "pass_L": 1,
    "pass_alpha": 1,
    "pass_el": 1,
    "elapsed": 5.5,
    "logs": {
      "step": [
        200,
        400,
        600,
        800,
        1000,
        1200,
        1400,
        1600,
        1800,
        2000,
        2200,
        2400,
        2600,
        2800,
        3000,
        3200,
        3400,
        3600,
        3800,
        4000,
        4200,
        4400,
        4600,
        4800
      ],
      "sigma": [
        7.631,
        7.631,
        7.631,
        7.631,
        7.631,
        7.631,
        7.631,
        7.631,
        7.631,
        7.631,
        7.631,
        7.631,
        7.631,
        7.631,
        7.631,
        7.631,
        7.631,
        7.631,
        7.631,
        7.631,
        7.631,
        7.633,
        7.633,
        7.633
      ],
      "C": [
        0.2625,
        0.2625,
        0.2625,
        0.2625,
        0.2625,
        0.2625,
        0.2625,
        0.2625,
        0.2625,
        0.2625,
        0.2625,
        0.2625,
        0.2625,
        0.2625,
        0.2625,
        0.2625,
        0.2625,
        0.2625,
        0.2625,
        0.2625,
        0.2625,
        0.2605,
        0.2605,
        0.2605
      ],
      "L": [
        3.411,
        3.411,
        3.411,
        3.411,
        3.411,
        3.411,
        3.411,
        3.411,
        3.411,
        3.411,
        3.411,
        3.411,
        3.411,
        3.411,
        3.411,
        3.411,
        3.411,
        3.411,
        3.411,
        3.411,
        3.411,
        3.38,
        3.38,
        3.38
      ],
      "alpha": [
        1.697,
        1.698,
        1.728,
        1.757,
        1.797,
        1.848,
        1.776,
        1.695,
        1.898,
        1.916,
        1.944,
        1.799,
        1.841,
        2.003,
        1.81,
        1.937,
        2.129,
        2.034,
        2.05,
        2.006,
        2.177,
        1.929,
        1.957,
        2.006
      ],
      "el": [
        0.0,
        0.0,
        0.0,
        0.0084,
        0.0504,
        0.1237,
        0.2027,
        0.2492,
        0.243,
        0.238,
        0.2324,
        0.2492,
        0.2256,
        0.2296,
        0.2452,
        0.2475,
        0.2475,
        0.2475,
        0.2391,
        0.229,
        0.2452,
        0.2452,
        0.238,
        0.2402
      ],
      "ne": [
        1786,
        1786,
        1786,
        1786,
        1786,
        1786,
        1786,
        1786,
        1786,
        1786,
        1786,
        1786,
        1786,
        1786,
        1786,
        1786,
        1786,
        1786,
        1786,
        1786,
        1786,
        1786,
        1786,
        1786
      ]
    },
    "score": 5
  },
  "Larval_Droso": {
    "sigma": 9.061294650662804,
    "C": 0.2680744921399127,
    "L": 3.4829638752052543,
    "alpha": 2.1570183215511065,
    "el": 0.24299065420560748,
    "pass_sigma": 1,
    "pass_C": 1,
    "pass_L": 1,
    "pass_alpha": 1,
    "pass_el": 1,
    "elapsed": 5.8,
    "logs": {
      "step": [
        200,
        400,
        600,
        800,
        1000,
        1200,
        1400,
        1600,
        1800,
        2000,
        2200,
        2400,
        2600,
        2800,
        3000,
        3200,
        3400,
        3600,
        3800,
        4000,
        4200,
        4400,
        4600,
        4800
      ],
      "sigma": [
        9.061,
        9.061,
        9.061,
        9.061,
        9.061,
        9.061,
        9.061,
        9.061,
        9.061,
        9.061,
        9.061,
        9.061,
        9.061,
        9.061,
        9.061,
        9.061,
        9.061,
        9.061,
        9.061,
        9.061,
        9.061,
        9.061,
        9.061,
        9.061
      ],
      "C": [
        0.2681,
        0.2681,
        0.2681,
        0.2681,
        0.2681,
        0.2681,
        0.2681,
        0.2681,
        0.2681,
        0.2681,
        0.2681,
        0.2681,
        0.2681,
        0.2681,
        0.2681,
        0.2681,
        0.2681,
        0.2681,
        0.2681,
        0.2681,
        0.2681,
        0.2681,
        0.2681,
        0.2681
      ],
      "L": [
        3.483,
        3.483,
        3.483,
        3.483,
        3.483,
        3.483,
        3.483,
        3.483,
        3.483,
        3.483,
        3.483,
        3.483,
        3.483,
        3.483,
        3.483,
        3.483,
        3.483,
        3.483,
        3.483,
        3.483,
        3.483,
        3.483,
        3.483,
        3.483
      ],
      "alpha": [
        1.826,
        1.968,
        1.844,
        1.877,
        1.85,
        2.009,
        1.875,
        1.9,
        1.966,
        1.894,
        1.968,
        2.219,
        2.132,
        2.023,
        2.083,
        2.003,
        2.022,
        2.014,
        2.203,
        2.18,
        1.988,
        2.052,
        2.208,
        2.078
      ],
      "el": [
        0.0,
        0.0,
        0.0,
        0.0118,
        0.0516,
        0.1038,
        0.1918,
        0.2258,
        0.2405,
        0.2376,
        0.2297,
        0.2307,
        0.243,
        0.2263,
        0.2391,
        0.2494,
        0.2332,
        0.2277,
        0.2489,
        0.2366,
        0.241,
        0.2445,
        0.245,
        0.2494
      ],
      "ne": [
        2033,
        2033,
        2033,
        2033,
        2033,
        2033,
        2033,
        2033,
        2033,
        2033,
        2033,
        2033,
        2033,
        2033,
        2033,
        2033,
        2033,
        2033,
        2033,
        2033,
        2033,
        2033,
        2033,
        2033
      ]
    },
    "score": 5
  },
  "Rat_Cortex": {
    "sigma": 1.3697605322628081,
    "C": 0.10661974176759122,
    "L": 2.5190972222222223,
    "alpha": 1.6329014190767714,
    "el": 0.23546511627906977,
    "pass_sigma": 0,
    "pass_C": 0,
    "pass_L": 1,
    "pass_alpha": 1,
    "pass_el": 1,
    "elapsed": 3.1,
    "logs": {
      "step": [
        200,
        400,
        600,
        800,
        1000,
        1200,
        1400,
        1600,
        1800,
        2000,
        2200,
        2400,
        2600,
        2800,
        3000,
        3200,
        3400,
        3600,
        3800,
        4000,
        4200,
        4400,
        4600,
        4800
      ],
      "sigma": [
        1.37,
        1.37,
        1.37,
        1.37,
        1.37,
        1.37,
        1.37,
        1.37,
        1.37,
        1.37,
        1.37,
        1.37,
        1.37,
        1.37,
        1.37,
        1.37,
        1.37,
        1.37,
        1.37,
        1.37,
        1.37,
        1.37,
        1.37,
        1.37
      ],
      "C": [
        0.1066,
        0.1066,
        0.1066,
        0.1066,
        0.1066,
        0.1066,
        0.1066,
        0.1066,
        0.1066,
        0.1066,
        0.1066,
        0.1066,
        0.1066,
        0.1066,
        0.1066,
        0.1066,
        0.1066,
        0.1066,
        0.1066,
        0.1066,
        0.1066,
        0.1066,
        0.1066,
        0.1066
      ],
      "L": [
        2.519,
        2.519,
        2.519,
        2.519,
        2.519,
        2.519,
        2.519,
        2.519,
        2.519,
        2.519,
        2.519,
        2.519,
        2.519,
        2.519,
        2.519,
        2.519,
        2.519,
        2.519,
        2.519,
        2.519,
        2.519,
        2.519,
        2.519,
        2.519
      ],
      "alpha": [
        1.471,
        1.633,
        1.456,
        1.616,
        1.654,
        1.652,
        1.645,
        1.586,
        1.666,
        1.659,
        1.661,
        1.465,
        1.655,
        1.668,
        1.644,
        1.638,
        1.615,
        1.622,
        1.597,
        1.617,
        1.62,
        1.638,
        1.879,
        1.627
      ],
      "el": [
        0.0,
        0.0174,
        0.1919,
        0.2384,
        0.2326,
        0.2355,
        0.25,
        0.2355,
        0.2326,
        0.2384,
        0.2384,
        0.2297,
        0.2384,
        0.2442,
        0.2471,
        0.2413,
        0.2442,
        0.2442,
        0.2471,
        0.2471,
        0.2355,
        0.2442,
        0.2413,
        0.2326
      ],
      "ne": [
        344,
        344,
        344,
        344,
        344,
        344,
        344,
        344,
        344,
        344,
        344,
        344,
        344,
        344,
        344,
        344,
        344,
        344,
        344,
        344,
        344,
        344,
        344,
        344
      ]
    },
    "score": 3
  },
  "Mouse_Cortex": {
    "sigma": 1.0949913948612837,
    "C": 0.05582852689290659,
    "L": 2.720720720720721,
    "alpha": 1.6184145725846193,
    "el": 0.24703557312252963,
    "pass_sigma": 0,
    "pass_C": 0,
    "pass_L": 1,
    "pass_alpha": 1,
    "pass_el": 1,
    "elapsed": 4.5,
    "logs": {
      "step": [
        200,
        400,
        600,
        800,
        1000,
        1200,
        1400,
        1600,
        1800,
        2000,
        2200,
        2400,
        2600,
        2800,
        3000,
        3200,
        3400,
        3600,
        3800,
        4000,
        4200,
        4400,
        4600,
        4800
      ],
      "sigma": [
        1.107,
        1.107,
        1.107,
        1.107,
        1.107,
        1.107,
        1.107,
        1.107,
        1.107,
        1.107,
        1.107,
        1.107,
        1.107,
        1.099,
        1.099,
        1.099,
        1.095,
        1.095,
        1.095,
        1.095,
        1.095,
        1.095,
        1.095,
        1.095
      ],
      "C": [
        0.056,
        0.056,
        0.056,
        0.056,
        0.056,
        0.056,
        0.056,
        0.056,
        0.056,
        0.056,
        0.056,
        0.056,
        0.056,
        0.0558,
        0.0558,
        0.0558,
        0.0558,
        0.0558,
        0.0558,
        0.0558,
        0.0558,
        0.0558,
        0.0558,
        0.0558
      ],
      "L": [
        2.727,
        2.727,
        2.727,
        2.727,
        2.727,
        2.727,
        2.727,
        2.727,
        2.727,
        2.727,
        2.727,
        2.727,
        2.727,
        2.725,
        2.725,
        2.725,
        2.721,
        2.721,
        2.721,
        2.721,
        2.721,
        2.721,
        2.721,
        2.721
      ],
      "alpha": [
        1.46,
        1.448,
        1.444,
        1.623,
        1.62,
        1.605,
        1.623,
        1.647,
        1.451,
        1.638,
        1.639,
        1.627,
        1.642,
        1.653,
        1.632,
        1.646,
        1.635,
        1.644,
        1.656,
        1.652,
        1.637,
        1.625,
        1.621,
        1.62
      ],
      "el": [
        0.0,
        0.0198,
        0.1542,
        0.2352,
        0.2312,
        0.2451,
        0.2391,
        0.2391,
        0.2411,
        0.2411,
        0.249,
        0.2273,
        0.2411,
        0.2273,
        0.2451,
        0.2411,
        0.249,
        0.2273,
        0.249,
        0.2372,
        0.2372,
        0.2411,
        0.2332,
        0.2292
      ],
      "ne": [
        506,
        506,
        506,
        506,
        506,
        506,
        506,
        506,
        506,
        506,
        506,
        506,
        506,
        506,
        506,
        506,
        506,
        506,
        506,
        506,
        506,
        506,
        506,
        506
      ]
    },
    "score": 3
  },
  "Macaque_Cortex": {
    "sigma": 3.8638673355057214,
    "C": 0.25291563484319923,
    "L": 2.4428367638068065,
    "alpha": 2.0694228728298376,
    "el": 0.22651128914785143,
    "pass_sigma": 1,
    "pass_C": 1,
    "pass_L": 1,
    "pass_alpha": 1,
    "pass_el": 1,
    "elapsed": 5.6,
    "logs": {
      "step": [
        200,
        400,
        600,
        800,
        1000,
        1200,
        1400,
        1600,
        1800,
        2000,
        2200,
        2400,
        2600,
        2800,
        3000,
        3200,
        3400,
        3600,
        3800,
        4000,
        4200,
        4400,
        4600,
        4800
      ],
      "sigma": [
        3.87,
        3.87,
        3.87,
        3.87,
        3.87,
        3.87,
        3.87,
        3.87,
        3.87,
        3.87,
        3.87,
        3.87,
        3.87,
        3.87,
        3.87,
        3.87,
        3.87,
        3.865,
        3.865,
        3.865,
        3.865,
        3.864,
        3.864,
        3.864
      ],
      "C": [
        0.2536,
        0.2536,
        0.2536,
        0.2536,
        0.2536,
        0.2536,
        0.2536,
        0.2536,
        0.2536,
        0.2536,
        0.2536,
        0.2536,
        0.2536,
        0.2536,
        0.2536,
        0.2536,
        0.2536,
        0.2533,
        0.2533,
        0.2533,
        0.2533,
        0.2529,
        0.2529,
        0.2529
      ],
      "L": [
        2.449,
        2.449,
        2.449,
        2.449,
        2.449,
        2.449,
        2.449,
        2.449,
        2.449,
        2.449,
        2.449,
        2.449,
        2.449,
        2.449,
        2.449,
        2.449,
        2.449,
        2.448,
        2.448,
        2.448,
        2.448,
        2.443,
        2.443,
        2.443
      ],
      "alpha": [
        1.527,
        1.516,
        1.663,
        1.623,
        1.632,
        2.076,
        1.88,
        1.859,
        1.998,
        2.076,
        2.469,
        2.053,
        1.954,
        1.919,
        1.989,
        1.919,
        1.825,
        1.772,
        1.711,
        1.91,
        1.897,
        1.949,
        1.95,
        2.026
      ],
      "el": [
        0.0,
        0.0,
        0.0284,
        0.1752,
        0.2258,
        0.2276,
        0.2287,
        0.2454,
        0.2323,
        0.2491,
        0.2345,
        0.2291,
        0.2254,
        0.2462,
        0.2261,
        0.2323,
        0.2462,
        0.2291,
        0.2305,
        0.2451,
        0.2425,
        0.2254,
        0.2429,
        0.2345
      ],
      "ne": [
        2746,
        2746,
        2746,
        2746,
        2746,
        2746,
        2746,
        2746,
        2746,
        2746,
        2746,
        2746,
        2746,
        2746,
        2746,
        2746,
        2746,
        2746,
        2746,
        2746,
        2746,
        2746,
        2746,
        2746
      ]
    },
    "score": 5
  }
}